segment_anything/__init__.py
segment_anything/automatic_mask_generator.py
segment_anything/build_sam.py
segment_anything/predictor.py
segment_anything/modeling/__init__.py
segment_anything/modeling/common.py
segment_anything/modeling/image_encoder.py
segment_anything/modeling/mask_decoder.py
segment_anything/modeling/prompt_encoder.py
segment_anything/modeling/sam.py
segment_anything/modeling/transformer.py
segment_anything/utils/__init__.py
segment_anything/utils/amg.py
segment_anything/utils/onnx.py
segment_anything/utils/transforms.py
visaionsegmentanything-1.0.dist-info/licenses/LICENSE
visaionsegmentanything-1.0.dist-info/METADATA
visaionsegmentanything-1.0.dist-info/WHEEL
visaionsegmentanything-1.0.dist-info/top_level.txt
visaionsegmentanything-1.0.dist-info/RECORD
